__init__.py
pelicanfs/__init__.py
pelicanfs/core.py
pelicanfs/dir_header_parser.py
pelicanfs/exceptions.py
pelicanfs/token_content_iterator.py
pelicanfs/token_generator.py
pelicanfs-1.3.0.dist-info/licenses/LICENSE
pelicanfs-1.3.0.dist-info/METADATA
pelicanfs-1.3.0.dist-info/WHEEL
pelicanfs-1.3.0.dist-info/entry_points.txt
pelicanfs-1.3.0.dist-info/top_level.txt
pelicanfs-1.3.0.dist-info/RECORD
