Metadata-Version: 2.4
Name: pelicanfs
Version: 1.3.0
Summary: An FSSpec Implementation using the Pelican System
Author-email: Pelican Platform Developers <info@pelicanplatform.org>
License-Expression: Apache-2.0
Project-URL: Source, https://github.com/PelicanPlatform/pelicanfs
Project-URL: Pelican-Source, https://github.com/PelicanPlatform/pelican
Project-URL: Bug-Reports, https://github.com/PelicanPlatform/pelicanfs/issues
Keywords: pelican,fsspec
Classifier: Development Status :: 2 - Pre-Alpha
Classifier: Intended Audience :: Science/Research
Classifier: Programming Language :: Python :: 3
Classifier: Programming Language :: Python :: 3.11
Classifier: Programming Language :: Python :: 3.12
Classifier: Programming Language :: Python :: 3.13
Classifier: Programming Language :: Python :: 3 :: Only
Requires-Python: <4,>=3.11
License-File: LICENSE
Requires-Dist: aiohttp<4,>=3.9.4
Requires-Dist: aiowebdav2
Requires-Dist: cachetools<6,>=5.3
Requires-Dist: fsspec>=2024.3.1
Requires-Dist: igwn-auth-utils
Requires-Dist: pywinpty; platform_system == "Windows"
Dynamic: license-file
